amdsharktank/__init__.py
amdsharktank/py.typed
amdsharktank/build/__init__.py
amdsharktank/build/actions.py
amdsharktank/evaluate/perplexity_iree.py
amdsharktank/evaluate/perplexity_torch.py
amdsharktank/examples/export_paged_llm_v1.py
amdsharktank/examples/paged_llm_v1.py
amdsharktank/examples/validate_paged_llama_model.py
amdsharktank/examples/pipeline/export_ppffn_net.py
amdsharktank/examples/sharding/export_ffn_net.py
amdsharktank/examples/sharding/export_gemm.py
amdsharktank/examples/sharding/shard_llm_dataset.py
amdsharktank/export_layer/export_kv_cache.py
amdsharktank/export_layer/export_moe.py
amdsharktank/export_layer/export_paged_attention.py
amdsharktank/kernels/__init__.py
amdsharktank/kernels/attention.py
amdsharktank/kernels/base.py
amdsharktank/kernels/batch_matmul_transpose_b.py
amdsharktank/kernels/bitcast.py
amdsharktank/kernels/conv_2d_nchw_fchw.py
amdsharktank/kernels/einsum_2args_q4.py
amdsharktank/kernels/gemm_fp4.py
amdsharktank/kernels/gemm_fp4_asm.py
amdsharktank/kernels/mlir_kernel.py
amdsharktank/kernels/mmt_block_scaled_offset_q4.py
amdsharktank/kernels/mmt_block_scaled_q8.py
amdsharktank/kernels/mmt_super_block_scaled_offset_q4.py
amdsharktank/kernels/mmtfp.py
amdsharktank/kernels/pooling_nchw_sum.py
amdsharktank/kernels/rotary.py
amdsharktank/kernels/topk.py
amdsharktank/kernels/templates/batch_matmul_transpose_b.mlir
amdsharktank/kernels/templates/conv_2d_nchw_fchw.mlir
amdsharktank/kernels/templates/einsum_2args_q4.mlir
amdsharktank/kernels/templates/mmt_block_scaled_offset_q4_unsigned.mlir
amdsharktank/kernels/templates/mmt_block_scaled_q8_3d.mlir
amdsharktank/kernels/templates/mmt_super_block_scaled_offset_q4_unsigned_3d.mlir
amdsharktank/kernels/templates/mmtfp_2d.mlir
amdsharktank/kernels/templates/mmtfp_3d.mlir
amdsharktank/kernels/templates/pooling_nchw_sum.mlir
amdsharktank/kernels/templates/rotary_embedding.mlir
amdsharktank/kernels/templates/topk_dynamic.mlir
amdsharktank/kernels/wave/attention.py
amdsharktank-3.9.0.dist-info/METADATA
amdsharktank-3.9.0.dist-info/WHEEL
amdsharktank-3.9.0.dist-info/entry_points.txt
amdsharktank-3.9.0.dist-info/top_level.txt
amdsharktank-3.9.0.dist-info/RECORD
